LabTest/2020-21 Parity_Checker/2017B5A70667P.v
module MEM1(S, G);
	input[2:0] S;
	output[8:0] G;
	reg[8:0] mem[0:7];
	
	reg[8:0] G;
	
	//Initialize the memory
	initial
	begin
		 mem[0] = 9'b000111111;  
		 mem[1] = 9'b001100011;  
		 mem[2] = 9'b010100111;  
		 mem[3] = 9'b011101011;  
		 mem[4] = 9'b100101111;  
		 mem[5] = 9'b101110011;  
		 mem[6] = 9'b110110111;  
		 mem[7] = 9'b111111011;  
	end
	
	always @(S)
		begin
			case(S)
				3'b000: G = mem[0];
				3'b001: G = mem[1];
				3'b010: G = mem[2];
				3'b011: G = mem[3];
				3'b100: G = mem[4];
				3'b101: G = mem[5];
				3'b110: G = mem[6];
				3'b111: G = mem[7];
			endcase
		
		end
endmodule

module MEM2(S, G);
	input[2:0] S;
	output[8:0] G;
	reg[8:0] mem[0:7];
	
	reg[8:0] G;
	
	//Initialize the memory
	initial
	begin
		 mem[0] = 9'b000000000;  
		 mem[1] = 9'b001000100;  
		 mem[2] = 9'b010001000;  
		 mem[3] = 9'b011001100;  
		 mem[4] = 9'b100010000;  
		 mem[5] = 9'b101010100;  
		 mem[6] = 9'b110011000;  
		 mem[7] = 9'b111011100;  
	end
	
	always @(S)
		begin
			case(S)
				3'b000: G = mem[0];
				3'b001: G = mem[1];
				3'b010: G = mem[2];
				3'b011: G = mem[3];
				3'b100: G = mem[4];
				3'b101: G = mem[5];
				3'b110: G = mem[6];
				3'b111: G = mem[7];
			endcase
		
		end
endmodule

module RSFF(q, qbar, r,s, clk, reset);
    input r,s, clk, reset;
    output q, qbar;

    reg q;
    wire qbar;
    assign qbar = ~q;
    initial 
        q <= 1'b0;
    always @(posedge clk or reset)
    begin
        if(reset)
            q <= 1'b0;
        else if(r & s)
            q <= 1'b0;
        else if(r & ~s)
            q <= 1'b0;
        else if(~r & s)
            q <= 1'b1;
    end
endmodule

module DFF(q, qbar, d, clk, reset);
    input d,clk,reset;
    output q,qbar;
    RSFF R(q, qbar, ~d,d, clk, reset);
endmodule

module Ripple_Counter(clk, reset, q);
    input clk, reset;
    output [3:0] q;

    wire [3:0] qbar;

    DFF DFF1(q[0], qbar[0], qbar[0], clk, reset);
    DFF DFF2(q[1], qbar[1], qbar[1], qbar[0], reset);
    DFF DFF3(q[2], qbar[2], qbar[2], qbar[1], reset);
    DFF DFF4(q[3], qbar[3], qbar[3], qbar[2], reset);

endmodule

module Parity_Checker(res,data8,data1);
    input data1;
    input [7:0]data8;
    output res;
    assign res=((data8[0]^data8[1]^data8[2]^data8[3]^data8[4]^data8[5]^data8[6]^data8[7])==data1)?1:0;
endmodule

module MUX2To1(sel, in1, in2, out);
	input sel, in1, in2;
	output out;
	assign out = (~sel & in1) | (sel & in2);
endmodule

module MUX16To8(sel,F, C, E);
	input[7:0] F, C;
    input sel;
	output[7:0] E;
		
	genvar j;
	
	generate for(j = 0; j < 8; j = j+1)
		begin: mux_loop
			MUX2To1 M21(sel,F[j], C[j], E[j]);
		end
	endgenerate
endmodule

module Fetch_Data(data,parity,RC);
    input [3:0] RC;
    output parity;
    output [7:0] data;
    wire [8:0] G1,G2;
    MEM1 MM(RC[2:0], G1);
    MEM2 MN(RC[2:0], G2);
    MUX2To1  MS2(RC[3],G1[0],G2[0],parity);
    MUX16To8 MS8(RC[3],G1[8:1],G2[8:1],data);
endmodule

module Design(res,clk,reset);
    input clk,reset;
    output res;
    wire [3:0] RC;
    wire parity;
    wire [7:0]data;
    Ripple_Counter R1(clk, reset, RC);
    Fetch_Data FD(data,parity,RC);
    Parity_Checker PC(res,data,parity);
endmodule

module tb;
    initial	
	begin
		$dumpfile("2017B5A70667P.vcd");
		$dumpvars;
	end
	reg clock, reset;
	wire res;
	
	Design D(res,clock,reset);
	initial
        begin
		clock = 1'b0;
        reset=1'b0;
        end
	always
		#2 clock <= ~clock;
	
	initial
		begin
			$monitor($time, " Value=%8b, Parity=%b, Output = %b",D.data,D.parity,res);
			#200 $finish;			
		end
endmodule

LabTest/2020-21 Parity_Checker/2017B5A70667P.vcd
$date
	Sun Nov  8 16:13:55 2020
$end
$version
	Icarus Verilog
$end
$timescale
	1s
$end
$scope module tb $end
$var wire 1 ! res $end
$var reg 1 " clock $end
$var reg 1 # reset $end
$scope module D $end
$var wire 1 " clk $end
$var wire 1 # reset $end
$var wire 1 ! res $end
$var wire 1 $ parity $end
$var wire 8 % data [7:0] $end
$var wire 4 & RC [3:0] $end
$scope module FD $end
$var wire 1 $ parity $end
$var wire 8 ' data [7:0] $end
$var wire 4 ( RC [3:0] $end
$var wire 9 ) G2 [8:0] $end
$var wire 9 * G1 [8:0] $end
$scope module MM $end
$var wire 3 + S [2:0] $end
$var reg 9 , G [8:0] $end
$upscope $end
$scope module MN $end
$var wire 3 - S [2:0] $end
$var reg 9 . G [8:0] $end
$upscope $end
$scope module MS2 $end
$var wire 1 / in1 $end
$var wire 1 0 in2 $end
$var wire 1 $ out $end
$var wire 1 1 sel $end
$upscope $end
$scope module MS8 $end
$var wire 8 2 C [7:0] $end
$var wire 8 3 F [7:0] $end
$var wire 1 4 sel $end
$var wire 8 5 E [7:0] $end
$scope begin mux_loop[0] $end
$scope module M21 $end
$var wire 1 6 in1 $end
$var wire 1 7 in2 $end
$var wire 1 8 out $end
$var wire 1 4 sel $end
$upscope $end
$upscope $end
$scope begin mux_loop[1] $end
$scope module M21 $end
$var wire 1 9 in1 $end
$var wire 1 : in2 $end
$var wire 1 ; out $end
$var wire 1 4 sel $end
$upscope $end
$upscope $end
$scope begin mux_loop[2] $end
$scope module M21 $end
$var wire 1 < in1 $end
$var wire 1 = in2 $end
$var wire 1 > out $end
$var wire 1 4 sel $end
$upscope $end
$upscope $end
$scope begin mux_loop[3] $end
$scope module M21 $end
$var wire 1 ? in1 $end
$var wire 1 @ in2 $end
$var wire 1 A out $end
$var wire 1 4 sel $end
$upscope $end
$upscope $end
$scope begin mux_loop[4] $end
$scope module M21 $end
$var wire 1 B in1 $end
$var wire 1 C in2 $end
$var wire 1 D out $end
$var wire 1 4 sel $end
$upscope $end
$upscope $end
$scope begin mux_loop[5] $end
$scope module M21 $end
$var wire 1 E in1 $end
$var wire 1 F in2 $end
$var wire 1 G out $end
$var wire 1 4 sel $end
$upscope $end
$upscope $end
$scope begin mux_loop[6] $end
$scope module M21 $end
$var wire 1 H in1 $end
$var wire 1 I in2 $end
$var wire 1 J out $end
$var wire 1 4 sel $end
$upscope $end
$upscope $end
$scope begin mux_loop[7] $end
$scope module M21 $end
$var wire 1 K in1 $end
$var wire 1 L in2 $end
$var wire 1 M out $end
$var wire 1 4 sel $end
$upscope $end
$upscope $end
$upscope $end
$upscope $end
$scope module PC $end
$var wire 1 $ data1 $end
$var wire 8 N data8 [7:0] $end
$var wire 1 ! res $end
$upscope $end
$scope module R1 $end
$var wire 1 " clk $end
$var wire 1 # reset $end
$var wire 4 O qbar [3:0] $end
$var wire 4 P q [3:0] $end
$scope module DFF1 $end
$var wire 1 " clk $end
$var wire 1 Q d $end
$var wire 1 # reset $end
$var wire 1 R qbar $end
$var wire 1 S q $end
$scope module R $end
$var wire 1 " clk $end
$var wire 1 R qbar $end
$var wire 1 T r $end
$var wire 1 # reset $end
$var wire 1 Q s $end
$var reg 1 S q $end
$upscope $end
$upscope $end
$scope module DFF2 $end
$var wire 1 U clk $end
$var wire 1 V d $end
$var wire 1 # reset $end
$var wire 1 W qbar $end
$var wire 1 X q $end
$scope module R $end
$var wire 1 U clk $end
$var wire 1 W qbar $end
$var wire 1 Y r $end
$var wire 1 # reset $end
$var wire 1 V s $end
$var reg 1 X q $end
$upscope $end
$upscope $end
$scope module DFF3 $end
$var wire 1 Z clk $end
$var wire 1 [ d $end
$var wire 1 # reset $end
$var wire 1 \ qbar $end
$var wire 1 ] q $end
$scope module R $end
$var wire 1 Z clk $end
$var wire 1 \ qbar $end
$var wire 1 ^ r $end
$var wire 1 # reset $end
$var wire 1 [ s $end
$var reg 1 ] q $end
$upscope $end
$upscope $end
$scope module DFF4 $end
$var wire 1 _ clk $end
$var wire 1 ` d $end
$var wire 1 # reset $end
$var wire 1 a qbar $end
$var wire 1 b q $end
$scope module R $end
$var wire 1 _ clk $end
$var wire 1 a qbar $end
$var wire 1 c r $end
$var wire 1 # reset $end
$var wire 1 ` s $end
$var reg 1 b q $end
$upscope $end
$upscope $end
$upscope $end
$upscope $end
$upscope $end
$enddefinitions $end
#0
$dumpvars
0c
0b
1a
1`
1_
0^
0]
1\
1[
1Z
0Y
0X
1W
1V
1U
0T
0S
1R
1Q
b0 P
b1111 O
b11111 N
0M
0L
0K
0J
0I
0H
0G
0F
0E
1D
0C
1B
1A
0@
1?
1>
0=
1<
1;
0:
19
18
07
16
b11111 5
04
b11111 3
b0 2
01
00
1/
b0 .
b0 -
b111111 ,
b0 +
b111111 *
b0 )
b0 (
b11111 '
b0 &
b11111 %
1$
0#
0"
1!
$end
#2
1!
0;
0>
0A
b110001 %
b110001 '
b110001 5
b110001 N
1G
1:
1F
09
0<
0?
1E
1T
b100010 2
b110001 3
0U
0Q
b1000100 )
b1000100 .
b1100011 *
b1100011 ,
b1110 O
0R
b1 -
b1 +
b1 &
b1 (
b1 P
1S
1"
#4
0"
#6
1J
1=
1I
1H
1Y
0Z
0V
0W
1X
0!
1;
0>
0A
b1010011 %
b1010011 '
b1010011 5
b1010011 N
0G
0:
0F
19
0<
0?
0E
0T
b1000100 2
b1010011 3
1U
1Q
b10001000 )
b10001000 .
b10100111 *
b10100111 ,
b1101 O
1R
b10 -
b10 +
b10 &
b10 (
b10 P
0S
1"
#8
0"
#10
1!
0;
1>
b1110101 %
b1110101 '
b1110101 5
b1110101 N
1G
1:
1F
09
1<
1E
1T
b1100110 2
b1110101 3
0U
0Q
b11001100 )
b11001100 .
b11101011 *
b11101011 ,
b1100 O
0R
b11 -
b11 +
b11 &
b11 (
b11 P
1S
1"
#12
0"
#14
1M
1@
1L
1K
1^
0_
0[
0\
1]
0A
0J
0=
0I
0?
0H
0Y
1Z
1V
1W
0X
1!
1;
1>
b10010111 %
b10010111 '
b10010111 5
b10010111 N
0G
0:
0F
19
1<
0E
0T
b10001000 2
b10010111 3
1U
1Q
b100010000 )
b100010000 .
b100101111 *
b100101111 ,
b1011 O
1R
b100 -
b100 +
b100 &
b100 (
b100 P
0S
1"
#16
0"
#18
1!
0;
0>
1A
b10111001 %
b10111001 '
b10111001 5
b10111001 N
1G
1:
1F
09
0<
1?
1E
1T
b10101010 2
b10111001 3
0U
0Q
b101010100 )
b101010100 .
b101110011 *
b101110011 ,
b1010 O
0R
b101 -
b101 +
b101 &
b101 (
b101 P
1S
1"
#20
0"
#22
1J
1=
1I
1H
1Y
0Z
0V
0W
1X
0!
1;
0>
1A
b11011011 %
b11011011 '
b11011011 5
b11011011 N
0G
0:
0F
19
0<
1?
0E
0T
b11001100 2
b11011011 3
1U
1Q
b110011000 )
b110011000 .
b110110111 *
b110110111 ,
b1001 O
1R
b110 -
b110 +
b110 &
b110 (
b110 P
0S
1"
#24
0"
#26
1!
0;
1>
b11111101 %
b11111101 '
b11111101 5
b11111101 N
1G
1:
1F
09
1<
1E
1T
b11101110 2
b11111101 3
0U
0Q
b111011100 )
b111011100 .
b111111011 *
b111111011 ,
b1000 O
0R
b111 -
b111 +
b111 &
b111 (
b111 P
1S
1"
#28
0"
#30
08
0D
0$
1c
0`
0a
14
11
1b
0M
0@
0L
0K
0^
1_
1[
1\
0]
0A
0J
0=
0I
1?
0H
0Y
1Z
1V
1W
0X
1!
0;
0>
b0 %
b0 '
b0 5
b0 N
0G
0:
0F
19
1<
0E
0T
b0 2
b11111 3
1U
1Q
b0 )
b0 .
b111111 *
b111111 ,
b111 O
1R
b0 -
b0 +
b1000 &
b1000 (
b1000 P
0S
1"
#32
0"
#34
1!
1;
b100010 %
b100010 '
b100010 5
b100010 N
1G
1:
1F
09
0<
0?
1E
1T
b100010 2
b110001 3
0U
0Q
b1000100 )
b1000100 .
b1100011 *
b1100011 ,
b110 O
0R
b1 -
b1 +
b1001 &
b1001 (
b1001 P
1S
1"
#36
0"
#38
1>
1J
1=
1I
1H
1Y
0Z
0V
0W
1X
1!
0;
b1000100 %
b1000100 '
b1000100 5
b1000100 N
0G
0:
0F
19
0<
0?
0E
0T
b1000100 2
b1010011 3
1U
1Q
b10001000 )
b10001000 .
b10100111 *
b10100111 ,
b101 O
1R
b10 -
b10 +
b1010 &
b1010 (
b1010 P
0S
1"
#40
0"
#42
1!
1;
b1100110 %
b1100110 '
b1100110 5
b1100110 N
1G
1:
1F
09
1<
1E
1T
b1100110 2
b1110101 3
0U
0Q
b11001100 )
b11001100 .
b11101011 *
b11101011 ,
b100 O
0R
b11 -
b11 +
b1011 &
b1011 (
b1011 P
1S
1"
#44
0"
#46
1A
1M
1@
1L
1K
1^
0_
0[
0\
1]
0>
0J
0=
0I
0?
0H
0Y
1Z
1V
1W
0X
1!
0;
b10001000 %
b10001000 '
b10001000 5
b10001000 N
0G
0:
0F
19
1<
0E
0T
b10001000 2
b10010111 3
1U
1Q
b100010000 )
b100010000 .
b100101111 *
b100101111 ,
b11 O
1R
b100 -
b100 +
b1100 &
b1100 (
b1100 P
0S
1"
#48
0"
#50
1!
1;
b10101010 %
b10101010 '
b10101010 5
b10101010 N
1G
1:
1F
09
0<
1?
1E
1T
b10101010 2
b10111001 3
0U
0Q
b101010100 )
b101010100 .
b101110011 *
b101110011 ,
b10 O
0R
b101 -
b101 +
b1101 &
b1101 (
b1101 P
1S
1"
#52
0"
#54
1>
1J
1=
1I
1H
1Y
0Z
0V
0W
1X
1!
0;
b11001100 %
b11001100 '
b11001100 5
b11001100 N
0G
0:
0F
19
0<
1?
0E
0T
b11001100 2
b11011011 3
1U
1Q
b110011000 )
b110011000 .
b110110111 *
b110110111 ,
b1 O
1R
b110 -
b110 +
b1110 &
b1110 (
b1110 P
0S
1"
#56
0"
#58
1!
1;
b11101110 %
b11101110 '
b11101110 5
b11101110 N
1G
1:
1F
09
1<
1E
1T
b11101110 2
b11111101 3
0U
0Q
b111011100 )
b111011100 .
b111111011 *
b111111011 ,
b0 O
0R
b111 -
b111 +
b1111 &
b1111 (
b1111 P
1S
1"
#60
0"
#62
18
1D
1$
0c
1`
1a
04
01
0b
1A
0M
0@
0L
0K
0^
1_
1[
1\
0]
1>
0J
0=
0I
1?
0H
0Y
1Z
1V
1W
0X
1!
1;
b11111 %
b11111 '
b11111 5
b11111 N
0G
0:
0F
19
1<
0E
0T
b0 2
b11111 3
1U
1Q
b0 )
b0 .
b111111 *
b111111 ,
b1111 O
1R
b0 -
b0 +
b0 &
b0 (
b0 P
0S
1"
#64
0"
#66
1!
0;
0>
0A
b110001 %
b110001 '
b110001 5
b110001 N
1G
1:
1F
09
0<
0?
1E
1T
b100010 2
b110001 3
0U
0Q
b1000100 )
b1000100 .
b1100011 *
b1100011 ,
b1110 O
0R
b1 -
b1 +
b1 &
b1 (
b1 P
1S
1"
#68
0"
#70
1J
1=
1I
1H
1Y
0Z
0V
0W
1X
0!
1;
0>
0A
b1010011 %
b1010011 '
b1010011 5
b1010011 N
0G
0:
0F
19
0<
0?
0E
0T
b1000100 2
b1010011 3
1U
1Q
b10001000 )
b10001000 .
b10100111 *
b10100111 ,
b1101 O
1R
b10 -
b10 +
b10 &
b10 (
b10 P
0S
1"
#72
0"
#74
1!
0;
1>
b1110101 %
b1110101 '
b1110101 5
b1110101 N
1G
1:
1F
09
1<
1E
1T
b1100110 2
b1110101 3
0U
0Q
b11001100 )
b11001100 .
b11101011 *
b11101011 ,
b1100 O
0R
b11 -
b11 +
b11 &
b11 (
b11 P
1S
1"
#76
0"
#78
1M
1@
1L
1K
1^
0_
0[
0\
1]
0A
0J
0=
0I
0?
0H
0Y
1Z
1V
1W
0X
1!
1;
1>
b10010111 %
b10010111 '
b10010111 5
b10010111 N
0G
0:
0F
19
1<
0E
0T
b10001000 2
b10010111 3
1U
1Q
b100010000 )
b100010000 .
b100101111 *
b100101111 ,
b1011 O
1R
b100 -
b100 +
b100 &
b100 (
b100 P
0S
1"
#80
0"
#82
1!
0;
0>
1A
b10111001 %
b10111001 '
b10111001 5
b10111001 N
1G
1:
1F
09
0<
1?
1E
1T
b10101010 2
b10111001 3
0U
0Q
b101010100 )
b101010100 .
b101110011 *
b101110011 ,
b1010 O
0R
b101 -
b101 +
b101 &
b101 (
b101 P
1S
1"
#84
0"
#86
1J
1=
1I
1H
1Y
0Z
0V
0W
1X
0!
1;
0>
1A
b11011011 %
b11011011 '
b11011011 5
b11011011 N
0G
0:
0F
19
0<
1?
0E
0T
b11001100 2
b11011011 3
1U
1Q
b110011000 )
b110011000 .
b110110111 *
b110110111 ,
b1001 O
1R
b110 -
b110 +
b110 &
b110 (
b110 P
0S
1"
#88
0"
#90
1!
0;
1>
b11111101 %
b11111101 '
b11111101 5
b11111101 N
1G
1:
1F
09
1<
1E
1T
b11101110 2
b11111101 3
0U
0Q
b111011100 )
b111011100 .
b111111011 *
b111111011 ,
b1000 O
0R
b111 -
b111 +
b111 &
b111 (
b111 P
1S
1"
#92
0"
#94
08
0D
0$
1c
0`
0a
14
11
1b
0M
0@
0L
0K
0^
1_
1[
1\
0]
0A
0J
0=
0I
1?
0H
0Y
1Z
1V
1W
0X
1!
0;
0>
b0 %
b0 '
b0 5
b0 N
0G
0:
0F
19
1<
0E
0T
b0 2
b11111 3
1U
1Q
b0 )
b0 .
b111111 *
b111111 ,
b111 O
1R
b0 -
b0 +
b1000 &
b1000 (
b1000 P
0S
1"
#96
0"
#98
1!
1;
b100010 %
b100010 '
b100010 5
b100010 N
1G
1:
1F
09
0<
0?
1E
1T
b100010 2
b110001 3
0U
0Q
b1000100 )
b1000100 .
b1100011 *
b1100011 ,
b110 O
0R
b1 -
b1 +
b1001 &
b1001 (
b1001 P
1S
1"
#100
0"
#102
1>
1J
1=
1I
1H
1Y
0Z
0V
0W
1X
1!
0;
b1000100 %
b1000100 '
b1000100 5
b1000100 N
0G
0:
0F
19
0<
0?
0E
0T
b1000100 2
b1010011 3
1U
1Q
b10001000 )
b10001000 .
b10100111 *
b10100111 ,
b101 O
1R
b10 -
b10 +
b1010 &
b1010 (
b1010 P
0S
1"
#104
0"
#106
1!
1;
b1100110 %
b1100110 '
b1100110 5
b1100110 N
1G
1:
1F
09
1<
1E
1T
b1100110 2
b1110101 3
0U
0Q
b11001100 )
b11001100 .
b11101011 *
b11101011 ,
b100 O
0R
b11 -
b11 +
b1011 &
b1011 (
b1011 P
1S
1"
#108
0"
#110
1A
1M
1@
1L
1K
1^
0_
0[
0\
1]
0>
0J
0=
0I
0?
0H
0Y
1Z
1V
1W
0X
1!
0;
b10001000 %
b10001000 '
b10001000 5
b10001000 N
0G
0:
0F
19
1<
0E
0T
b10001000 2
b10010111 3
1U
1Q
b100010000 )
b100010000 .
b100101111 *
b100101111 ,
b11 O
1R
b100 -
b100 +
b1100 &
b1100 (
b1100 P
0S
1"
#112
0"
#114
1!
1;
b10101010 %
b10101010 '
b10101010 5
b10101010 N
1G
1:
1F
09
0<
1?
1E
1T
b10101010 2
b10111001 3
0U
0Q
b101010100 )
b101010100 .
b101110011 *
b101110011 ,
b10 O
0R
b101 -
b101 +
b1101 &
b1101 (
b1101 P
1S
1"
#116
0"
#118
1>
1J
1=
1I
1H
1Y
0Z
0V
0W
1X
1!
0;
b11001100 %
b11001100 '
b11001100 5
b11001100 N
0G
0:
0F
19
0<
1?
0E
0T
b11001100 2
b11011011 3
1U
1Q
b110011000 )
b110011000 .
b110110111 *
b110110111 ,
b1 O
1R
b110 -
b110 +
b1110 &
b1110 (
b1110 P
0S
1"
#120
0"
#122
1!
1;
b11101110 %
b11101110 '
b11101110 5
b11101110 N
1G
1:
1F
09
1<
1E
1T
b11101110 2
b11111101 3
0U
0Q
b111011100 )
b111011100 .
b111111011 *
b111111011 ,
b0 O
0R
b111 -
b111 +
b1111 &
b1111 (
b1111 P
1S
1"
#124
0"
#126
18
1D
1$
0c
1`
1a
04
01
0b
1A
0M
0@
0L
0K
0^
1_
1[
1\
0]
1>
0J
0=
0I
1?
0H
0Y
1Z
1V
1W
0X
1!
1;
b11111 %
b11111 '
b11111 5
b11111 N
0G
0:
0F
19
1<
0E
0T
b0 2
b11111 3
1U
1Q
b0 )
b0 .
b111111 *
b111111 ,
b1111 O
1R
b0 -
b0 +
b0 &
b0 (
b0 P
0S
1"
#128
0"
#130
1!
0;
0>
0A
b110001 %
b110001 '
b110001 5
b110001 N
1G
1:
1F
09
0<
0?
1E
1T
b100010 2
b110001 3
0U
0Q
b1000100 )
b1000100 .
b1100011 *
b1100011 ,
b1110 O
0R
b1 -
b1 +
b1 &
b1 (
b1 P
1S
1"
#132
0"
#134
1J
1=
1I
1H
1Y
0Z
0V
0W
1X
0!
1;
0>
0A
b1010011 %
b1010011 '
b1010011 5
b1010011 N
0G
0:
0F
19
0<
0?
0E
0T
b1000100 2
b1010011 3
1U
1Q
b10001000 )
b10001000 .
b10100111 *
b10100111 ,
b1101 O
1R
b10 -
b10 +
b10 &
b10 (
b10 P
0S
1"
#136
0"
#138
1!
0;
1>
b1110101 %
b1110101 '
b1110101 5
b1110101 N
1G
1:
1F
09
1<
1E
1T
b1100110 2
b1110101 3
0U
0Q
b11001100 )
b11001100 .
b11101011 *
b11101011 ,
b1100 O
0R
b11 -
b11 +
b11 &
b11 (
b11 P
1S
1"
#140
0"
#142
1M
1@
1L
1K
1^
0_
0[
0\
1]
0A
0J
0=
0I
0?
0H
0Y
1Z
1V
1W
0X
1!
1;
1>
b10010111 %
b10010111 '
b10010111 5
b10010111 N
0G
0:
0F
19
1<
0E
0T
b10001000 2
b10010111 3
1U
1Q
b100010000 )
b100010000 .
b100101111 *
b100101111 ,
b1011 O
1R
b100 -
b100 +
b100 &
b100 (
b100 P
0S
1"
#144
0"
#146
1!
0;
0>
1A
b10111001 %
b10111001 '
b10111001 5
b10111001 N
1G
1:
1F
09
0<
1?
1E
1T
b10101010 2
b10111001 3
0U
0Q
b101010100 )
b101010100 .
b101110011 *
b101110011 ,
b1010 O
0R
b101 -
b101 +
b101 &
b101 (
b101 P
1S
1"
#148
0"
#150
1J
1=
1I
1H
1Y
0Z
0V
0W
1X
0!
1;
0>
1A
b11011011 %
b11011011 '
b11011011 5
b11011011 N
0G
0:
0F
19
0<
1?
0E
0T
b11001100 2
b11011011 3
1U
1Q
b110011000 )
b110011000 .
b110110111 *
b110110111 ,
b1001 O
1R
b110 -
b110 +
b110 &
b110 (
b110 P
0S
1"
#152
0"
#154
1!
0;
1>
b11111101 %
b11111101 '
b11111101 5
b11111101 N
1G
1:
1F
09
1<
1E
1T
b11101110 2
b11111101 3
0U
0Q
b111011100 )
b111011100 .
b111111011 *
b111111011 ,
b1000 O
0R
b111 -
b111 +
b111 &
b111 (
b111 P
1S
1"
#156
0"
#158
08
0D
0$
1c
0`
0a
14
11
1b
0M
0@
0L
0K
0^
1_
1[
1\
0]
0A
0J
0=
0I
1?
0H
0Y
1Z
1V
1W
0X
1!
0;
0>
b0 %
b0 '
b0 5
b0 N
0G
0:
0F
19
1<
0E
0T
b0 2
b11111 3
1U
1Q
b0 )
b0 .
b111111 *
b111111 ,
b111 O
1R
b0 -
b0 +
b1000 &
b1000 (
b1000 P
0S
1"
#160
0"
#162
1!
1;
b100010 %
b100010 '
b100010 5
b100010 N
1G
1:
1F
09
0<
0?
1E
1T
b100010 2
b110001 3
0U
0Q
b1000100 )
b1000100 .
b1100011 *
b1100011 ,
b110 O
0R
b1 -
b1 +
b1001 &
b1001 (
b1001 P
1S
1"
#164
0"
#166
1>
1J
1=
1I
1H
1Y
0Z
0V
0W
1X
1!
0;
b1000100 %
b1000100 '
b1000100 5
b1000100 N
0G
0:
0F
19
0<
0?
0E
0T
b1000100 2
b1010011 3
1U
1Q
b10001000 )
b10001000 .
b10100111 *
b10100111 ,
b101 O
1R
b10 -
b10 +
b1010 &
b1010 (
b1010 P
0S
1"
#168
0"
#170
1!
1;
b1100110 %
b1100110 '
b1100110 5
b1100110 N
1G
1:
1F
09
1<
1E
1T
b1100110 2
b1110101 3
0U
0Q
b11001100 )
b11001100 .
b11101011 *
b11101011 ,
b100 O
0R
b11 -
b11 +
b1011 &
b1011 (
b1011 P
1S
1"
#172
0"
#174
1A
1M
1@
1L
1K
1^
0_
0[
0\
1]
0>
0J
0=
0I
0?
0H
0Y
1Z
1V
1W
0X
1!
0;
b10001000 %
b10001000 '
b10001000 5
b10001000 N
0G
0:
0F
19
1<
0E
0T
b10001000 2
b10010111 3
1U
1Q
b100010000 )
b100010000 .
b100101111 *
b100101111 ,
b11 O
1R
b100 -
b100 +
b1100 &
b1100 (
b1100 P
0S
1"
#176
0"
#178
1!
1;
b10101010 %
b10101010 '
b10101010 5
b10101010 N
1G
1:
1F
09
0<
1?
1E
1T
b10101010 2
b10111001 3
0U
0Q
b101010100 )
b101010100 .
b101110011 *
b101110011 ,
b10 O
0R
b101 -
b101 +
b1101 &
b1101 (
b1101 P
1S
1"
#180
0"
#182
1>
1J
1=
1I
1H
1Y
0Z
0V
0W
1X
1!
0;
b11001100 %
b11001100 '
b11001100 5
b11001100 N
0G
0:
0F
19
0<
1?
0E
0T
b11001100 2
b11011011 3
1U
1Q
b110011000 )
b110011000 .
b110110111 *
b110110111 ,
b1 O
1R
b110 -
b110 +
b1110 &
b1110 (
b1110 P
0S
1"
#184
0"
#186
1!
1;
b11101110 %
b11101110 '
b11101110 5
b11101110 N
1G
1:
1F
09
1<
1E
1T
b11101110 2
b11111101 3
0U
0Q
b111011100 )
b111011100 .
b111111011 *
b111111011 ,
b0 O
0R
b111 -
b111 +
b1111 &
b1111 (
b1111 P
1S
1"
#188
0"
#190
18
1D
1$
0c
1`
1a
04
01
0b
1A
0M
0@
0L
0K
0^
1_
1[
1\
0]
1>
0J
0=
0I
1?
0H
0Y
1Z
1V
1W
0X
1!
1;
b11111 %
b11111 '
b11111 5
b11111 N
0G
0:
0F
19
1<
0E
0T
b0 2
b11111 3
1U
1Q
b0 )
b0 .
b111111 *
b111111 ,
b1111 O
1R
b0 -
b0 +
b0 &
b0 (
b0 P
0S
1"
#192
0"
#194
1!
0;
0>
0A
b110001 %
b110001 '
b110001 5
b110001 N
1G
1:
1F
09
0<
0?
1E
1T
b100010 2
b110001 3
0U
0Q
b1000100 )
b1000100 .
b1100011 *
b1100011 ,
b1110 O
0R
b1 -
b1 +
b1 &
b1 (
b1 P
1S
1"
#196
0"
#198
1J
1=
1I
1H
1Y
0Z
0V
0W
1X
0!
1;
0>
0A
b1010011 %
b1010011 '
b1010011 5
b1010011 N
0G
0:
0F
19
0<
0?
0E
0T
b1000100 2
b1010011 3
1U
1Q
b10001000 )
b10001000 .
b10100111 *
b10100111 ,
b1101 O
1R
b10 -
b10 +
b10 &
b10 (
b10 P
0S
1"
