LAB 03/code/FSM.v
module FSM( clk, rst, inp, outp);
    initial
        begin
          $dumpfile("FSM.vcd");
          $dumpvars;
        end
    input clk, rst, inp;
    output reg outp;
    reg [2:0] state;
    always @( posedge clk, posedge rst ) 
        begin
            if( rst ) 
                begin
                    state <= 3'b000;
                    outp <= 0;
                end
            else 
                begin
                    case( state )
                        3'b000: 
                        begin
                            if( inp ) 
                                begin
                                    state <= 3'b001;
                                    outp <= 0;
                                end
                            else 
                                begin
                                    state <= 3'b000;
                                    outp <= 0;
                                end
                        end
                        3'b001: 
                        begin
                            if( inp ) 
                                begin
                                    state <= 3'b001;
                                    outp <= 0;
                                end
                            else 
                                begin
                                    state <= 3'b010;
                                    outp <= 0;
                                end
                        end
                        3'b010: 
                        begin
                            if( inp ) 
                                begin
                                    state <= 3'b011;
                                    outp <= 0;
                                end
                            else 
                                begin
                                    state <= 3'b000;
                                    outp <= 0;
                                end
                        end
                        3'b011: 
                        begin
                            if( inp ) 
                                begin
                                    state <= 3'b100;
                                    outp <= 0;
                                end
                            else 
                                begin
                                    state <= 3'b010;
                                    outp <= 0;
                                end
                        end
                        3'b100: 
                        begin
                            if( inp ) 
                                begin
                                    state <= 3'b001;
                                    outp <= 0;
                                end
                            else 
                                begin
                                    state <= 3'b010;
                                    outp <= 1;
                                end
                        end
                        default: 
                        begin
                            state <= 3'b000;
                            outp <= 0;
                        end
                    endcase
                end
        end
endmodule

module testbench;
    reg clk, rst, inp;
    wire outp;
    reg[15:0] sequence;
    integer i;
    FSM duty( clk, rst, inp, outp);
    initial
        begin
            clk = 1;
            rst = 1;
            sequence = 16'b0101_0101_1011_0100;
            #5 rst = 0;
            for( i = 0; i <= 15; i = i + 1)
            begin
                inp = sequence[i];
                #2 clk = 0;
                #2 clk = 1;
                $display(,$time," State = ", duty.state, " Input = ", inp, ", Output = ",outp);
            end
        end
endmodule

LAB 03/code/FSM.vcd
$date
	Mon Oct 26 22:48:15 2020
$end
$version
	Icarus Verilog
$end
$timescale
	1s
$end
$scope module testbench $end
$var wire 1 ! outp $end
$var reg 1 " clk $end
$var reg 1 # inp $end
$var reg 1 $ rst $end
$var reg 16 % sequence [15:0] $end
$var integer 32 & i [31:0] $end
$scope module duty $end
$var wire 1 " clk $end
$var wire 1 # inp $end
$var wire 1 $ rst $end
$var reg 1 ! outp $end
$var reg 3 ' state [2:0] $end
$upscope $end
$upscope $end
$enddefinitions $end
#0
$dumpvars
b0 '
bx &
b101010110110100 %
1$
x#
1"
0!
$end
#5
0#
b0 &
0$
#7
0"
#9
b1 &
1"
#11
0"
#13
b1 '
1#
b10 &
1"
#15
0"
#17
b10 '
0#
b11 &
1"
#19
0"
#21
b11 '
1#
b100 &
1"
#23
0"
#25
b100 '
b101 &
1"
#27
0"
#29
1!
b10 '
0#
b110 &
1"
#31
0"
#33
0!
b11 '
1#
b111 &
1"
#35
0"
#37
b100 '
b1000 &
1"
#39
0"
#41
1!
b10 '
0#
b1001 &
1"
#43
0"
#45
0!
b11 '
1#
b1010 &
1"
#47
0"
#49
b10 '
0#
b1011 &
1"
#51
0"
#53
b11 '
1#
b1100 &
1"
#55
0"
#57
b10 '
0#
b1101 &
1"
#59
0"
#61
b11 '
1#
b1110 &
1"
#63
0"
#65
b10 '
0#
b1111 &
1"
#67
0"
#69
b0 '
b10000 &
1"
